{"version":"1.0.0","name":"ProCrafters-Bots","dependencies":{"@malept/cross-spawn-promise":{"version":"1.1.1"},"@types/fs-extra":{"version":"9.0.13"},"@types/glob":{"version":"7.2.0"},"@types/minimatch":{"version":"3.0.5"},"ansi-styles":{"version":"4.3.0"},"at-least-node":{"version":"1.0.0"},"child_process":{"version":"1.0.2"},"cliui":{"version":"6.0.0"},"color-name":{"version":"1.1.4"},"electron-installer-common":{"version":"0.10.3"},"electron-installer-debian":{"version":"3.1.0"},"emoji-regex":{"version":"8.0.0"},"fs":{"version":"0.0.1-security"},"gar":{"version":"1.0.4"},"get-caller-file":{"version":"2.0.5"},"get-folder-size":{"version":"2.0.1"},"isexe":{"version":"2.0.0"},"lodash":{"version":"4.17.21"},"lru-cache":{"version":"6.0.0"},"require-directory":{"version":"2.1.1"},"require-main-filename":{"version":"2.0.0"},"set-blocking":{"version":"2.0.0"},"tiny-each-async":{"version":"2.0.3"},"tmp-promise":{"version":"3.0.3"},"which-module":{"version":"2.0.0"},"word-wrap":{"version":"1.2.3"},"wrap-ansi":{"version":"6.2.0"},"xterm":{"version":"4.19.0"},"y18n":{"version":"4.0.3"},"yallist":{"version":"4.0.0"},"yargs":{"version":"15.4.1"}}}